tests/__init__.py
tests/test_files.py
tests/test_token_transformer.py
tests/test_vector_db.py
vectoriz/__init__.py
vectoriz/files.py
vectoriz/token_transformer.py
vectoriz/vector_db.py
vectoriz-1.0.1.dist-info/METADATA
vectoriz-1.0.1.dist-info/WHEEL
vectoriz-1.0.1.dist-info/top_level.txt
vectoriz-1.0.1.dist-info/RECORD
