Metadata-Version: 2.4
Name: vectoriz
Version: 1.0.1
Summary: Python library for creating vectorized data from text or files.
Home-page: https://github.com/PedroHenriqueDevBR/vectoriz
Author: PedroHenriqueDevBR
Author-email: pedro.henrique.particular@gmail.com
Classifier: Programming Language :: Python :: 3.12
Classifier: Operating System :: OS Independent
Requires-Python: >=3.12
Requires-Dist: faiss-cpu==1.10.0
Requires-Dist: numpy==2.2.4
Requires-Dist: sentence-transformers==4.0.2
Requires-Dist: python-docx==1.1.2
Dynamic: author
Dynamic: author-email
Dynamic: classifier
Dynamic: description
Dynamic: description-content-type
Dynamic: home-page
Dynamic: requires-dist
Dynamic: requires-python
Dynamic: summary
